setup.py
django_mirror_map/__init__.py
django_mirror_map.egg-info/PKG-INFO
django_mirror_map.egg-info/SOURCES.txt
django_mirror_map.egg-info/dependency_links.txt
django_mirror_map.egg-info/entry_points.txt
django_mirror_map.egg-info/top_level.txt