Metadata-Version: 1.0
Name: django-mirror-map
Version: 0.0.6
Summary: 查找某个属性的映射属性
Home-page: https://github.com/shi1fan
Author: shiyifan17
Author-email: shiyifan17@163.com
License: UNKNOWN
Platform: UNKNOWN
